[
  {
    "filename": "Network_Lists_Bajaj_Allianz.pdf",
    "reason": "PDF read error: pdf is not a function"
  },
  {
    "filename": "Galaxy_Health_Insurance.pdf",
    "reason": "PDF read error: pdf is not a function"
  },
  {
    "filename": "New_India_Assurance.pdf",
    "reason": "PDF read error: pdf is not a function"
  },
  {
    "filename": "Reliance.pdf",
    "reason": "PDF read error: pdf is not a function"
  },
  {
    "filename": "Network_Lists_Tata_AIG.pdf",
    "reason": "PDF read error: pdf is not a function"
  },
  {
    "filename": "HDFC_ERGO.pdf",
    "reason": "PDF read error: pdf is not a function"
  },
  {
    "filename": "ICICI_Lombard.pdf",
    "reason": "PDF read error: pdf is not a function"
  },
  {
    "filename": "Star_Health_Super_Star_Value.pdf",
    "reason": "PDF read error: pdf is not a function"
  },
  {
    "filename": "Niva_Bupa_(formerly_known_as_Max_Bupa).pdf",
    "reason": "PDF read error: pdf is not a function"
  },
  {
    "filename": "Care_Health.pdf",
    "reason": "PDF read error: pdf is not a function"
  },
  {
    "filename": "Kotak_General_Insurance.pdf",
    "reason": "PDF read error: pdf is not a function"
  },
  {
    "filename": "Network_Lists_Aditya_Birla.pdf",
    "reason": "PDF read error: pdf is not a function"
  },
  {
    "filename": "MAGMA_HDI.pdf",
    "reason": "PDF read error: pdf is not a function"
  },
  {
    "filename": "Universal_Sompo.pdf",
    "reason": "PDF read error: pdf is not a function"
  },
  {
    "filename": "Zuno.pdf",
    "reason": "PDF read error: pdf is not a function"
  },
  {
    "filename": "ManipalCigna.pdf",
    "reason": "PDF read error: pdf is not a function"
  }
]