{
    "niva_bupa": "Niva Bupa Health Insurance Company Limited",
    "max_bupa": "Niva Bupa Health Insurance Company Limited",
    "hdfc_ergo": "HDFC ERGO General Insurance Company Limited",
    "star_health": "Star Health and Allied Insurance Co Ltd",
    "icici_lombard": "ICICI Lombard General Insurance Company Limited",
    "care_health": "Care Health Insurance Limited",
    "religare": "Care Health Insurance Limited",
    "aditya_birla": "Aditya Birla Health Insurance Co. Limited",
    "manipal_cigna": "ManipalCigna Health Insurance Company Limited",
    "bajaj_allianz": "Bajaj Allianz General Insurance Company Limited",
    "tata_aig": "Tata AIG General Insurance Company Limited",
    "sbi_general": "SBI General Insurance Company Limited",
    "acko": "Acko General Insurance Limited",
    "navi": "Navi General Insurance Limited",
    "reliance": "Reliance General Insurance Company Limited",
    "digit": "Go Digit General Insurance Limited"
}